{"id":"su-front-don","country":"SU","side":"soviet","branch":"rkka","echelon":"front","type":"hq","short":"Don F.","names":[{"from":"1942-09-28","name":"Don Front","aliases":["Донской фронт","Donskoy front"]}],"existence":[{"from":"1942-09-28","to":"1943-02-15","end":"redesignated Central Front"}],"parents":[],"children":[{"from":"1943-01-01","to":"1943-02-15","unit":"su-army-62","label":"62nd Army"},{"from":"1943-01-01","to":"1943-02-15","unit":"su-army-64","label":"64th Army"}],"positions":[],"positionsTo":null,"links":{"wikipedia.en":"https://en.wikipedia.org/wiki/Don_Front","pamyat-naroda":"https://pamyat-naroda.ru/"},"sources":[],"notes":"Scaffold (no positions yet). Rokossovsky; conducted Operation Ring."}